ntust_courses/__init__.py
ntust_courses/core.py
ntust_courses-0.2.1.dist-info/METADATA
ntust_courses-0.2.1.dist-info/WHEEL
ntust_courses-0.2.1.dist-info/top_level.txt
ntust_courses-0.2.1.dist-info/RECORD
