Metadata-Version: 2.4
Name: ntust-courses
Version: 0.2.1
Summary: NTUST Class Querier
Author: xinshoutw
Requires-Dist: build>=1.3.0
Requires-Dist: requests
